vujade/__init__.py
vujade/main_encdec.py
vujade/main_img2vid.py
vujade/main_profiler.py
vujade/main_profiler_gpu_android.py
vujade/vujade_argparse.py
vujade/vujade_aws.py
vujade/vujade_blender.py
vujade/vujade_builtins.py
vujade/vujade_bytes.py
vujade/vujade_compression.py
vujade/vujade_cryptography.py
vujade/vujade_csv.py
vujade/vujade_datastructure.py
vujade/vujade_debug.py
vujade/vujade_download.py
vujade/vujade_erase.py
vujade/vujade_face.py
vujade/vujade_flops_counter.py
vujade/vujade_google.py
vujade/vujade_gradio.py
vujade/vujade_handler.py
vujade/vujade_imgcv.py
vujade/vujade_ism.py
vujade/vujade_json.py
vujade/vujade_kube.py
vujade/vujade_list.py
vujade/vujade_logger.py
vujade/vujade_loss.py
vujade/vujade_lr_scheduler.py
vujade/vujade_math.py
vujade/vujade_metric.py
vujade/vujade_multiprocess.py
vujade/vujade_multithread.py
vujade/vujade_network.py
vujade/vujade_nms.py
vujade/vujade_numpy.py
vujade/vujade_omegaconf.py
vujade/vujade_onnx.py
vujade/vujade_openai.py
vujade/vujade_opencv.py
vujade/vujade_pandas.py
vujade/vujade_path.py
vujade/vujade_profiler.py
vujade/vujade_progressbar.py
vujade/vujade_pyvista.py
vujade/vujade_quic.py
vujade/vujade_random.py
vujade/vujade_resource.py
vujade/vujade_segmentation.py
vujade/vujade_slack.py
vujade/vujade_str.py
vujade/vujade_tensorboard.py
vujade/vujade_tensorflow.py
vujade/vujade_text.py
vujade/vujade_time.py
vujade/vujade_torch.py
vujade/vujade_transforms.py
vujade/vujade_utils.py
vujade/vujade_videocv.py
vujade/vujade_warnings.py
vujade/vujade_wavefront.py
vujade/vujade_xlsx.py
vujade/vujade_yaml.py
vujade/transformation/__init__.py
vujade/transformation/face_parsing.py
vujade/transformation/image_restoration.py
vujade-2.0.0.dist-info/LICENSE
vujade-2.0.0.dist-info/METADATA
vujade-2.0.0.dist-info/WHEEL
vujade-2.0.0.dist-info/top_level.txt
vujade-2.0.0.dist-info/RECORD
