Metadata-Version: 2.1
Name: vujade
Version: 2.0.0
Home-page: https://github.com/vujadeyoon/vujade-python
Author: vujadeyoon
Author-email: vujadeyoon@gmail.com
License: MIT License
Keywords: vujade-python,vujade
Classifier: Development Status :: 5 - Production/Stable
Classifier: Operating System :: OS Independent
Classifier: License :: OSI Approved :: MIT License
Classifier: Natural Language :: English
Classifier: Programming Language :: Python :: 3.7
Classifier: Programming Language :: Python :: 3.8
Classifier: Programming Language :: Python :: 3.9
Classifier: Programming Language :: Python :: 3.10
Requires-Python: >=3.7
License-File: LICENSE
Requires-Dist: Cython
Requires-Dist: numpy
Requires-Dist: wheel
